dynarehelper/__init__.py
dynarehelper/dynare_simul.m
dynarehelper/dynare_simul_.mex
dynarehelper-0.0.5.dist-info/DESCRIPTION.rst
dynarehelper-0.0.5.dist-info/METADATA
dynarehelper-0.0.5.dist-info/RECORD
dynarehelper-0.0.5.dist-info/WHEEL
dynarehelper-0.0.5.dist-info/metadata.json
dynarehelper-0.0.5.dist-info/top_level.txt
