Metadata-Version: 2.0
Name: dynarehelper
Version: 0.0.5
Summary: A package for using Dynare++ and Octave to solve dynamic stochastic general equilibrium (DSGE) models
Home-page: https://github.com/letsgoexploring/dynarehelper-package
Author: Brian C. Jenkins
Author-email: bcjenkin@uci.edu
License: UNKNOWN
Keywords: economics,solution,dsge,macroconomics,rbc,new keynesian,business cycles,dynare,dynare++,octave
Platform: UNKNOWN
